supertokens_jwt_ref/__init__.py
supertokens_jwt_ref/access_token.py
supertokens_jwt_ref/access_token_singingkey.py
supertokens_jwt_ref/constant.py
supertokens_jwt_ref/cookie_and_header.py
supertokens_jwt_ref/exceptions.py
supertokens_jwt_ref/jwt.py
supertokens_jwt_ref/models.py
supertokens_jwt_ref/refresh_token.py
supertokens_jwt_ref/refresh_token_signing_key.py
supertokens_jwt_ref/session.py
supertokens_jwt_ref/session_helper.py
supertokens_jwt_ref/settings.py
supertokens_jwt_ref/supertokens.py
supertokens_jwt_ref/utils.py
supertokens_jwt_ref-2.0.0.dist-info/LICENSE.txt
supertokens_jwt_ref-2.0.0.dist-info/METADATA
supertokens_jwt_ref-2.0.0.dist-info/RECORD
supertokens_jwt_ref-2.0.0.dist-info/WHEEL
supertokens_jwt_ref-2.0.0.dist-info/top_level.txt
